<?xml version="1.0" encoding="UTF-8"?>
<dvbi:ServiceList version="45" id="tag:dvb.org,2024:ref-example_rev1" xml:lang="en"
    xmlns:dvbi="urn:dvb:metadata:servicediscovery:2024" xmlns:dvbi-types="urn:dvb:metadata:servicediscovery-types:2023" xmlns:tva="urn:tva:metadata:2024"
    xmlns:xsi="http://www.w3.org/2001/XMLSchema-instance"
    xsi:schemaLocation="urn:dvb:metadata:servicediscovery:2024 schemas/dvbi_v6.0.xsd">
  <dvbi:Name>DVB-I Reference app availability example</dvbi:Name>
  <dvbi:ProviderName>DVB</dvbi:ProviderName>
  <dvbi:LCNTableList>
    <dvbi:LCNTable>
      <dvbi:LCN channelNumber="1" serviceRef="tag:dvb.org,2020:rev1sid1"></dvbi:LCN>
      <dvbi:LCN channelNumber="2" serviceRef="tag:dvb.org,2020:rev1sid2"/>
    </dvbi:LCNTable>
  </dvbi:LCNTableList>
  <dvbi:ContentGuideSource CGSID="cgid-1">
    <dvbi:ProviderName>DVB-I Reference Application</dvbi:ProviderName>
    <dvbi:ScheduleInfoEndpoint contentType="application/xml">
      <dvbi-types:URI>INSTALL~~LOCATION/backend/schedule.php</dvbi-types:URI>
    </dvbi:ScheduleInfoEndpoint>
    <dvbi:ProgramInfoEndpoint contentType="application/xml">
      <dvbi-types:URI>INSTALL~~LOCATION/backend/program_information.php</dvbi-types:URI>
    </dvbi:ProgramInfoEndpoint>
    <dvbi:MoreEpisodesEndpoint contentType="application/xml">
      <dvbi-types:URI>INSTALL~~LOCATION/backend/more_episodes.php</dvbi-types:URI>
    </dvbi:MoreEpisodesEndpoint>
  </dvbi:ContentGuideSource>
  <dvbi:Service version="1">
    <dvbi:UniqueIdentifier>tag:dvb.org,2020:rev1sid1</dvbi:UniqueIdentifier>
    <dvbi:ServiceInstance priority="1">
      <dvbi:Availability>
        <dvbi:Period>
          <dvbi:Interval startTime="00:00:00Z" endTime="00:10:00Z"/>
        </dvbi:Period>
      </dvbi:Availability>
      <dvbi:DASHDeliveryParameters>
        <dvbi:UriBasedLocation contentType="application/dash+xml">
          <dvbi-types:URI>https://refapp.hbbtv.org/livesim/02_llamanofragv1/manifest.mpd</dvbi-types:URI>
        </dvbi:UriBasedLocation>
      </dvbi:DASHDeliveryParameters>
    </dvbi:ServiceInstance>
    <dvbi:ServiceName xml:lang="en">Not available service</dvbi:ServiceName>
    <dvbi:ServiceName xml:lang="fi">Ei saatavilla palvelu</dvbi:ServiceName>
    <dvbi:ServiceName xml:lang="zh">没有可用的服务</dvbi:ServiceName>
    <dvbi:ProviderName>DVB</dvbi:ProviderName>
    <dvbi:RelatedMaterial>
      <tva:HowRelated href="urn:dvb:metadata:cs:HowRelatedCS:2021:1000.1"></tva:HowRelated>
      <tva:MediaLocator>
        <tva:MediaUri contentType="image/png">INSTALL~~LOCATION/backend/channel_icons/outofservice_example.png</tva:MediaUri>
      </tva:MediaLocator>
    </dvbi:RelatedMaterial>
    <dvbi:ServiceType href="urn:dvb:metadata:cs:ServiceTypeCS:2019:linear"></dvbi:ServiceType>
  </dvbi:Service>
 <dvbi:Service version="11">
    <dvbi:UniqueIdentifier>tag:dvb.org,2020:rev1sid2</dvbi:UniqueIdentifier>
    <dvbi:ServiceInstance priority="1">
      <dvbi:DASHDeliveryParameters>
        <dvbi:UriBasedLocation contentType="application/dash+xml">
          <dvbi-types:URI>https://refapp.hbbtv.org/livesim/02_llamanofragv1/manifest.mpd</dvbi-types:URI>
        </dvbi:UriBasedLocation>
      </dvbi:DASHDeliveryParameters>
    </dvbi:ServiceInstance>
    <dvbi:ServiceName xml:lang="en">Available service</dvbi:ServiceName>
    <dvbi:ServiceName xml:lang="fi">Saatavilla palvelu</dvbi:ServiceName>
    <dvbi:ServiceName xml:lang="zh">可用服务</dvbi:ServiceName>
    <dvbi:ProviderName>DVB</dvbi:ProviderName>
    <dvbi:ServiceType href="urn:dvb:metadata:cs:ServiceTypeCS:2019:linear"></dvbi:ServiceType>
  </dvbi:Service>
</dvbi:ServiceList>
